fuse_data/__init__.py
fuse_data/_modidx.py
fuse_data/core.py
fuse_data-0.0.1.dist-info/LICENSE
fuse_data-0.0.1.dist-info/METADATA
fuse_data-0.0.1.dist-info/WHEEL
fuse_data-0.0.1.dist-info/entry_points.txt
fuse_data-0.0.1.dist-info/top_level.txt
fuse_data-0.0.1.dist-info/RECORD
